magentic/__init__.py
magentic/_chat.py
magentic/_parsing.py
magentic/_pydantic.py
magentic/_streamed_response.py
magentic/backend.py
magentic/chatprompt.py
magentic/formatting.py
magentic/function_call.py
magentic/logger.py
magentic/prompt_chain.py
magentic/prompt_function.py
magentic/py.typed
magentic/settings.py
magentic/streaming.py
magentic/typing.py
magentic/vision.py
magentic/chat_model/__init__.py
magentic/chat_model/anthropic_chat_model.py
magentic/chat_model/base.py
magentic/chat_model/function_schema.py
magentic/chat_model/litellm_chat_model.py
magentic/chat_model/message.py
magentic/chat_model/mistral_chat_model.py
magentic/chat_model/openai_chat_model.py
magentic/chat_model/openrouter_chat_model.py
magentic/chat_model/retry_chat_model.py
magentic/chat_model/stream.py
magentic-0.41.0.dist-info/METADATA
magentic-0.41.0.dist-info/WHEEL
magentic-0.41.0.dist-info/licenses/LICENSE
magentic-0.41.0.dist-info/RECORD
