Metadata-Version: 2.4
Name: magentic
Version: 0.41.0
Summary: Seamlessly integrate LLMs as Python functions
License-File: LICENSE
Requires-Python: >=3.10
Requires-Dist: filetype>=1.2.0
Requires-Dist: logfire-api>=0.1.0
Requires-Dist: openai>=1.108.1
Requires-Dist: pydantic-settings>=2.0.0
Requires-Dist: pydantic>=2.10.0
Requires-Dist: typing-extensions>=4.5.0
Provides-Extra: anthropic
Requires-Dist: anthropic>=0.41.0; extra == 'anthropic'
Provides-Extra: litellm
Requires-Dist: litellm>=1.41.12; extra == 'litellm'
